{
  "IcoMoonType": "selection",
  "icons": [
    {
      "icon": {
        "paths": [
          "M521.143 969.143c0-5.143-4-9.143-9.143-9.143-45.143 0-82.286-37.143-82.286-82.286 0-5.143-4-9.143-9.143-9.143s-9.143 4-9.143 9.143c0 55.429 45.143 100.571 100.571 100.571 5.143 0 9.143-4 9.143-9.143zM140.571 804.571h742.857c-102.286-115.429-152-272-152-475.429 0-73.714-69.714-182.857-219.429-182.857s-219.429 109.143-219.429 182.857c0 203.429-49.714 360-152 475.429zM987.429 804.571c0 40-33.143 73.143-73.143 73.143h-256c0 80.571-65.714 146.286-146.286 146.286s-146.286-65.714-146.286-146.286h-256c-40 0-73.143-33.143-73.143-73.143 84.571-71.429 182.857-199.429 182.857-475.429 0-109.714 90.857-229.714 242.286-252-2.857-6.857-4.571-14.286-4.571-22.286 0-30.286 24.571-54.857 54.857-54.857s54.857 24.571 54.857 54.857c0 8-1.714 15.429-4.571 22.286 151.429 22.286 242.286 142.286 242.286 252 0 276 98.286 404 182.857 475.429z"
        ],
        "width": 1024,
        "attrs": [],
        "isMulticolor": false,
        "isMulticolor2": false,
        "tags": [
          "bell-o"
        ],
        "defaultCode": 61602,
        "grid": 14
      },
      "attrs": [],
      "properties": {
        "name": "bell-o",
        "id": 153,
        "order": 2,
        "prevSize": 28,
        "code": 61602
      },
      "setIdx": 8,
      "setId": 11,
      "iconIdx": 153
    },
    {
      "icon": {
        "paths": [
          "M512.051 399.36c-62.208 0-112.691 50.432-112.691 112.64s50.483 112.64 112.691 112.64c62.208 0 112.589-50.432 112.589-112.64s-50.381-112.64-112.589-112.64zM153.651 399.36c-62.208 0-112.691 50.432-112.691 112.64s50.483 112.64 112.691 112.64c62.208 0 112.589-50.483 112.589-112.64s-50.381-112.64-112.589-112.64zM870.451 399.36c-62.208 0-112.691 50.432-112.691 112.64s50.483 112.64 112.691 112.64c62.208 0 112.589-50.432 112.589-112.64s-50.381-112.64-112.589-112.64z"
        ],
        "attrs": [],
        "isMulticolor": false,
        "isMulticolor2": false,
        "tags": [
          "dots-three-horizontal"
        ],
        "grid": 20
      },
      "attrs": [],
      "properties": {
        "id": 60,
        "order": 8,
        "prevSize": 20,
        "code": 59649,
        "name": "dots-three-horizontal"
      },
      "setIdx": 9,
      "setId": 10,
      "iconIdx": 59
    },
    {
      "icon": {
        "paths": [
          "M298.667 42.667h426.667q53 0 90.5 37.5t37.5 90.5v810.667l-341.333-256-341.333 256v-810.667q0-53 37.5-90.5t90.5-37.5zM725.333 128h-426.667q-17.667 0-30.167 12.5t-12.5 30.167v640l256-192 256 192v-640q0-17.667-12.5-30.167t-30.167-12.5z"
        ],
        "attrs": [],
        "isMulticolor": false,
        "isMulticolor2": false,
        "tags": [
          "ribbon"
        ],
        "defaultCode": 57353,
        "grid": 24
      },
      "attrs": [],
      "properties": {
        "id": 10,
        "order": 4,
        "prevSize": 24,
        "code": 57353,
        "name": "ribbon"
      },
      "setIdx": 12,
      "setId": 7,
      "iconIdx": 9
    }
  ],
  "height": 1024,
  "metadata": {
    "name": "icomoon"
  },
  "preferences": {
    "showGlyphs": true,
    "showQuickUse": true,
    "showQuickUse2": true,
    "showSVGs": true,
    "fontPref": {
      "prefix": "icon-",
      "metadata": {
        "fontFamily": "icomoon"
      },
      "metrics": {
        "emSize": 1024,
        "baseline": 6.25,
        "whitespace": 50
      },
      "embed": false
    },
    "imagePref": {
      "prefix": "icon-",
      "png": true,
      "useClassSelector": true,
      "color": 0,
      "bgColor": 16777215,
      "classSelector": ".icon"
    },
    "historySize": 50,
    "showCodes": true,
    "gridSize": 16
  }
}